uniqueWordList/__init__.py
uniqueWordList/uniqueWordList.py
uniquewordlist-0.0.1.dist-info/METADATA
uniquewordlist-0.0.1.dist-info/WHEEL
uniquewordlist-0.0.1.dist-info/RECORD
