Metadata-Version: 2.1
Name: uniqueWordList
Version: 0.0.1
Summary: Creates an object with a list of each unique word in a plaintext document.
Project-URL: Homepage, https://github.com/jondekerh/uniqueWords
Project-URL: Issues, https://github.com/jondekerh/uniqueWords/issues
Author-email: Jon Houston <jondekerh@gmail.com>
Classifier: License :: OSI Approved :: MIT License
Classifier: Operating System :: OS Independent
Classifier: Programming Language :: Python :: 3
Requires-Python: >=3.8
